Workbook
Name IQ_CH: 110000
Name IQ_CQ: 5000
Name IQ_CY: 10000
Name IQ_DAILY: 500000
Name IQ_FH: 100000
Name IQ_FQ: 500
Name IQ_FY: 1000
Name IQ_LTM: 2000
Name IQ_MONTH: 15000
Name IQ_NTM: 6000
Name IQ_WEEK: 50000
Name IQ_YTD: 3000

Sheet M&M PROJECT 3 Statement
A1: MAHINDRA AND MAHINDRA LTD PROJECT
B6: Historical Financial Statement - Mahindra and Mahindra Ltd
B7: Years | C7: 43921 | D7: 44286 | E7: 44651 | F7: 45016 | G7: 45382 | H7: 45747
A9: # | B9: Income statement
B10: Sales | C10: ='[1]Data Sheet'!F17 -> 75381.93 | D10: ='[1]Data Sheet'!G17 -> 74277.78 | E10: ='[1]Data Sheet'!H17 -> 90170.57 | F10: ='[1]Data Sheet'!I17 -> 121268.55 | G10: ='[1]Data Sheet'!J17 -> 139078.27 | H10: ='[1]Data Sheet'!K17 -> 159210.82
B11: sales growth % | D11: =IFERROR(D10/C10-1,0) -> -0.01464741 | E11: =E10/D10-1 -> 0.21396426 | F11: =F10/E10-1 -> 0.34487949 | G11: =G10/F10-1 -> 0.14686182 | H11: =H10/G10-1 -> 0.14475698
B13: COGS | C13: =IFERROR(SUM('[1]Data Sheet'!$F$18,'[1]Data Sheet'!$F$20:$F$22)-1*'[1]Data Sheet'!$F$19,0) -> 50445.45 | D13: =IFERROR(SUM('[1]Data Sheet'!G18,'[1]Data Sheet'!G20:G22)-1*'[1]Data Sheet'!G19,0) -> 49173.01 | E13: =IFERROR(SUM('[1]Data Sheet'!H18,'[1]Data Sheet'!H20:H22)-1*'[1]Data Sheet'!H19,0) -> 63855.47 | F13: =IFERROR(SUM('[1]Data Sheet'!I18,'[1]Data Sheet'!I20:I22)-1*'[1]Data Sheet'!I19,0) -> 88334.41 | G13: =IFERROR(SUM('[1]Data Sheet'!J18,'[1]Data Sheet'!J20:J22)-1*'[1]Data Sheet'!J19,0) -> 98783.56 | H13: =IFERROR(SUM('[1]Data Sheet'!K18,'[1]Data Sheet'!K20:K22)-1*'[1]Data Sheet'!K19,0) -> 111863.52
B14: COGS % Sales | C14: =C13/C10 -> 0.66919818 | D14: =D13/D10 -> 0.66201507 | E14: =E13/E10 -> 0.7081631 | F14: =F13/F10 -> 0.72841978 | G14: =G13/G10 -> 0.71027314 | H14: =H13/H10 -> 0.70261255
B16: Gross Profit | C16: =C10-C13 -> 24936.48 | D16: =D10-D13 -> 25104.77 | E16: =E10-E13 -> 26315.1 | F16: =F10-F13 -> 32934.14 | G16: =G10-G13 -> 40294.71 | H16: =H10-H13 -> 47347.3
B17: Gross Margins | C17: =C16/C10 -> 0.33080182 | D17: =D16/D10 -> 0.33798493 | E17: =E16/E10 -> 0.2918369 | F17: =F16/F10 -> 0.27158022 | G17: =G16/G10 -> 0.28972686 | H17: =H16/H10 -> 0.29738745
B19: Selling & General Expenses | C19: =IFERROR(SUM('[1]Data Sheet'!F23:F24),0) -> 14778.73 | D19: =IFERROR(SUM('[1]Data Sheet'!G23:G24),0) -> 13617.75 | E19: =IFERROR(SUM('[1]Data Sheet'!H23:H24),0) -> 11632.25 | F19: =IFERROR(SUM('[1]Data Sheet'!I23:I24),0) -> 12648.85 | G19: =IFERROR(SUM('[1]Data Sheet'!J23:J24),0) -> 15402.78 | H19: =IFERROR(SUM('[1]Data Sheet'!K23:K24),0) -> 16829.11
B20: S&G Exp % Sales | C20: =C19/C10 -> 0.19605136 | D20: =D19/D10 -> 0.18333545 | E20: =E19/E10 -> 0.12900273 | F20: =F19/F10 -> 0.10430445 | G20: =G19/G10 -> 0.110749 | H20: =H19/H10 -> 0.10570331
B22: EBITDA | C22: =C16-C19 -> 10157.75 | D22: =D16-D19 -> 11487.02 | E22: =E16-E19 -> 14682.85 | F22: =F16-F19 -> 20285.29 | G22: =G16-G19 -> 24891.93 | H22: =H16-H19 -> 30518.19
B23: EBITDA Margins | C23: =C22/C10 -> 0.13475046 | D23: =D22/D10 -> 0.15464948 | E23: =E22/E10 -> 0.16283417 | F23: =F22/F10 -> 0.16727577 | G23: =G22/G10 -> 0.17897785 | H23: =H22/H10 -> 0.19168415
B25: Interest | C25: ='[1]Data Sheet'!F27 -> 6021.15 | D25: ='[1]Data Sheet'!G27 -> 6102.22 | E25: ='[1]Data Sheet'!H27 -> 5018.05 | F25: ='[1]Data Sheet'!I27 -> 5829.7 | G25: ='[1]Data Sheet'!J27 -> 7488.21 | H25: ='[1]Data Sheet'!K27 -> 9083.39
B26: Interest % Sales | C26: =C25/C10 -> 0.079875243 | D26: =D25/D10 -> 0.082154044 | E26: =E25/E10 -> 0.055650641 | F26: =F25/F10 -> 0.048072645 | G26: =G25/G10 -> 0.053841696 | H26: =H25/H10 -> 0.057052592
B28: Depreciation | C28: ='[1]Data Sheet'!F26 -> 3366.68 | D28: ='[1]Data Sheet'!G26 -> 3378.11 | E28: ='[1]Data Sheet'!H26 -> 3507.5 | F28: ='[1]Data Sheet'!I26 -> 4356.81 | G28: ='[1]Data Sheet'!J26 -> 4723.78 | H28: ='[1]Data Sheet'!K26 -> 6073.65
B29: Depreciation%Sales | C29: =C28/C10 -> 0.044661632 | D29: =D28/D10 -> 0.045479415 | E29: =E28/E10 -> 0.038898501 | F29: =F28/F10 -> 0.035926957 | G29: =G28/G10 -> 0.033964903 | H29: =H28/H10 -> 0.038148475
B31: Earnings Before Tax | C31: =C22-(SUM(C25,C28)) -> 769.92 | D31: =D22-(SUM(D25,D28)) -> 2006.69 | E31: =E22-(SUM(E25,E28)) -> 6157.3 | F31: =F22-(SUM(F25,F28)) -> 10098.78 | G31: =G22-(SUM(G25,G28)) -> 12679.94 | H31: =H22-(SUM(H25,H28)) -> 15361.15
B32: EBT % Sales | C32: =C31/C10 -> 0.010213588 | D32: =D31/D10 -> 0.02701602 | E32: =E31/E10 -> 0.068285029 | F32: =F31/F10 -> 0.083276167 | G32: =G31/G10 -> 0.091171252 | H32: =H31/H10 -> 0.096483078
B34: Other Income | C34: ='[1]Data Sheet'!F25 -> 884.69 | D34: ='[1]Data Sheet'!G25 -> 1151.51 | E34: ='[1]Data Sheet'!H25 -> 3204.47 | F34: ='[1]Data Sheet'!I25 -> 3961.45 | G34: ='[1]Data Sheet'!J25 -> 3297.85 | H34: ='[1]Data Sheet'!K25 -> 3718.47
B35: other income % Sales | C35: =C34/C10 -> 0.011736102 | D35: =D34/D10 -> 0.015502752 | E35: =E34/E10 -> 0.03553787 | F35: =F34/F10 -> 0.032666755 | G35: =G34/G10 -> 0.023712187 | H35: =H34/H10 -> 0.023355636
B37: Tax | C37: ='[1]Data Sheet'!F29 -> 1975.61 | D37: ='[1]Data Sheet'!G29 -> 1645.81 | E37: ='[1]Data Sheet'!H29 -> 2108.76 | F37: ='[1]Data Sheet'!I29 -> 2685.75 | G37: ='[1]Data Sheet'!J29 -> 3707.97 | H37: ='[1]Data Sheet'!K29 -> 5006.45
B38: Effective Tax Rate | C38: =C37/SUM(C31,C34) -> 1.1940034 | D38: =D37/SUM(D31,D34) -> 0.52112279 | E38: =E37/SUM(E31,E34) -> 0.22525228 | F38: =F37/SUM(F31,F34) -> 0.1910175 | G38: =G37/SUM(G31,G34) -> 0.23207027 | H38: =H37/SUM(H31,H34) -> 0.26239778
B40: Net Profit | C40: =SUM(C31,C34)-C37 -> -321 | D40: =SUM(D31,D34)-D37 -> 1512.39 | E40: =SUM(E31,E34)-E37 -> 7253.01 | F40: =SUM(F31,F34)-F37 -> 11374.48 | G40: =SUM(G31,G34)-G37 -> 12269.82 | H40: =SUM(H31,H34)-H37 -> 14073.17
B41: Net Margins % | C41: =C40/C10 -> -0.004258315 | D41: =D40/D10 -> 0.020361271 | E41: =E40/E10 -> 0.080436555 | F41: =F40/F10 -> 0.093795795 | G41: =G40/G10 -> 0.088222409 | H41: =H40/H10 -> 0.088393301
B43: No of Equity Shares | C43: ='[1]Data Sheet'!F94 -> 124.32 | D43: ='[1]Data Sheet'!G94 -> 124.32 | E43: ='[1]Data Sheet'!H94 -> 124.32 | F43: ='[1]Data Sheet'!I94 -> 124.35 | G43: ='[1]Data Sheet'!J94 -> 124.35 | H43: ='[1]Data Sheet'!K94 -> 124.35
B45: Earnings per Share | C45: =C40/C43 -> -2.5820463 | D45: =D40/D43 -> 12.165299 | E45: =E40/E43 -> 58.341458 | F45: =F40/F43 -> 91.471492 | G45: =G40/G43 -> 98.671653 | H45: =H40/H43 -> 113.17386
B46: EPS Growth % | D46: =D45/C45-1 -> -5.7114953 | E46: =E45/D45-1 -> 3.7957273 | F46: =F45/E45-1 -> 0.56786436 | G46: =G45/F45-1 -> 0.078714807 | H46: =H45/G45-1 -> 0.14697445
B48: Dividend per Share | C48: ='[1]Data Sheet'!F31/'M&M PROJECT 3 Statement'!C43 -> 2.0954794 | D48: ='[1]Data Sheet'!G31/'M&M PROJECT 3 Statement'!D43 -> 7.8145914 | E48: ='[1]Data Sheet'!H31/'M&M PROJECT 3 Statement'!E43 -> 10.332207 | F48: ='[1]Data Sheet'!I31/'M&M PROJECT 3 Statement'!F43 -> 14.552955 | G48: ='[1]Data Sheet'!J31/'M&M PROJECT 3 Statement'!G43 -> 18.91548 | H48: ='[1]Data Sheet'!K31/'M&M PROJECT 3 Statement'!H43 -> 22.712023
B49: Dividend payout ratio | C49: =C48/C45 -> -0.81155763 | D49: =D48/D45 -> 0.64236738 | E49: =E48/E45 -> 0.17709889 | F49: =F48/F45 -> 0.15909826 | G49: =G48/G45 -> 0.19170126 | H49: =H48/H45 -> 0.20068258
A52: # | B52: Balance Sheet
B53: Equity Share Capital | C53: ='[1]Data Sheet'!F57 -> 554.28 | D53: ='[1]Data Sheet'!G57 -> 555.15 | E53: ='[1]Data Sheet'!H57 -> 556.06 | F53: ='[1]Data Sheet'!I57 -> 556.82 | G53: ='[1]Data Sheet'!J57 -> 557.38 | H53: ='[1]Data Sheet'!K57 -> 558.15
B54: Reserves | C54: ='[1]Data Sheet'!F58 -> 39415.03 | D54: ='[1]Data Sheet'!G58 -> 41026.77 | E54: ='[1]Data Sheet'!H58 -> 46566.58 | F54: ='[1]Data Sheet'!I58 -> 55808.97 | G54: ='[1]Data Sheet'!J58 -> 65633.17 | H54: ='[1]Data Sheet'!K58 -> 76480.71
B55: Borrowings | C55: ='[1]Data Sheet'!F59 -> 82092.28 | D55: ='[1]Data Sheet'!G59 -> 80624.83 | E55: ='[1]Data Sheet'!H59 -> 77605.21 | F55: ='[1]Data Sheet'!I59 -> 92246.85 | G55: ='[1]Data Sheet'!J59 -> 108647.25 | H55: ='[1]Data Sheet'!K59 -> 129024.58
B56: Other Liabilities | C56: ='[1]Data Sheet'!F60 -> 43654.54 | D56: ='[1]Data Sheet'!G60 -> 42761.58 | E56: ='[1]Data Sheet'!H60 -> 47660.64 | F56: ='[1]Data Sheet'!I60 -> 55670.49 | G56: ='[1]Data Sheet'!J60 -> 59883.94 | H56: ='[1]Data Sheet'!K60 -> 69949.72
B57: Total Liabilities | C57: =SUM('M&M PROJECT 3 Statement'!C53:C56) -> 165716.13 | D57: =SUM('M&M PROJECT 3 Statement'!D53:D56) -> 164968.33 | E57: =SUM('M&M PROJECT 3 Statement'!E53:E56) -> 172388.49 | F57: =SUM('M&M PROJECT 3 Statement'!F53:F56) -> 204283.13 | G57: =SUM('M&M PROJECT 3 Statement'!G53:G56) -> 234721.74 | H57: =SUM('M&M PROJECT 3 Statement'!H53:H56) -> 276013.16
B59: Fixed Assets Net Block | C59: ='[1]Data Sheet'!F62 -> 29689.27 | D59: ='[1]Data Sheet'!G62 -> 21379.68 | E59: ='[1]Data Sheet'!H62 -> 26018.49 | F59: ='[1]Data Sheet'!I62 -> 27139.98 | G59: ='[1]Data Sheet'!J62 -> 28129.41 | H59: ='[1]Data Sheet'!K62 -> 34636.36
B60: Capital Work in Progress | C60: ='[1]Data Sheet'!F63 -> 6856.48 | D60: ='[1]Data Sheet'!G63 -> 7872.61 | E60: ='[1]Data Sheet'!H63 -> 6702.81 | F60: ='[1]Data Sheet'!I63 -> 3968.58 | G60: ='[1]Data Sheet'!J63 -> 8039.3 | H60: ='[1]Data Sheet'!K63 -> 8297.64
B61: Investments | C61: ='[1]Data Sheet'!F64 -> 19210.34 | D61: ='[1]Data Sheet'!G64 -> 28777.66 | E61: ='[1]Data Sheet'!H64 -> 30060.43 | F61: ='[1]Data Sheet'!I64 -> 35272.42 | G61: ='[1]Data Sheet'!J64 -> 35208.1 | H61: ='[1]Data Sheet'!K64 -> 41308.57
B62: Other Assets | C62: ='[1]Data Sheet'!F65 -> 109960.04 | D62: ='[1]Data Sheet'!G65 -> 106938.38 | E62: ='[1]Data Sheet'!H65 -> 109606.76 | F62: ='[1]Data Sheet'!I65 -> 137902.15 | G62: ='[1]Data Sheet'!J65 -> 163344.93 | H62: ='[1]Data Sheet'!K65 -> 191770.59
B63: Total Non CurrentAssets | C63: =SUM(C59:C62) -> 165716.13 | D63: =SUM(D59:D62) -> 164968.33 | E63: =SUM(E59:E62) -> 172388.49 | F63: =SUM(F59:F62) -> 204283.13 | G63: =SUM(G59:G62) -> 234721.74 | H63: =SUM(H59:H62) -> 276013.16
B65: Receivables | C65: ='[1]Data Sheet'!F67 -> 6928.28 | D65: ='[1]Data Sheet'!G67 -> 6007.76 | E65: ='[1]Data Sheet'!H67 -> 6373.95 | F65: ='[1]Data Sheet'!I67 -> 7028.02 | G65: ='[1]Data Sheet'!J67 -> 7459.4 | H65: ='[1]Data Sheet'!K67 -> 8279.7
B66: Inventory | C66: ='[1]Data Sheet'!F68 -> 11111.86 | D66: ='[1]Data Sheet'!G68 -> 9615.41 | E66: ='[1]Data Sheet'!H68 -> 11595.82 | F66: ='[1]Data Sheet'!I68 -> 16854.97 | G66: ='[1]Data Sheet'!J68 -> 18590.47 | H66: ='[1]Data Sheet'!K68 -> 20330.93
B67: Cash & Bank | C67: ='[1]Data Sheet'!F69 -> 7910.9 | D67: ='[1]Data Sheet'!G69 -> 12851.99 | E67: ='[1]Data Sheet'!H69 -> 11117.61 | F67: ='[1]Data Sheet'!I69 -> 11273.43 | G67: ='[1]Data Sheet'!J69 -> 12012.75 | H67: ='[1]Data Sheet'!K69 -> 20614.84
B68: Total Current Assets | C68: =SUM(C65:C67) -> 25951.04 | D68: =SUM(D65:D67) -> 28475.16 | E68: =SUM(E65:E67) -> 29087.38 | F68: =SUM(F65:F67) -> 35156.42 | G68: =SUM(G65:G67) -> 38062.62 | H68: =SUM(H65:H67) -> 49225.47
B70: Total Assets | C70: =C63 -> 165716.13 | D70: =D63 -> 164968.33 | E70: =E63 -> 172388.49 | F70: =F63 -> 204283.13 | G70: =G63 -> 234721.74 | H70: =H63 -> 276013.16
B72: check | C72: =C70=C57 -> TRUE | D72: =D70=D57 -> TRUE | E72: =E70=E57 -> TRUE | F72: =F70=F57 -> TRUE | G72: =G70=G57 -> TRUE | H72: =H70=H57 -> TRUE
A74: # | B74: Cashflow Statement
B75: Operating activities
B76: Profit from operations | C76: ='[1]Raw Data (Source)'!K55 -> 7774 | D76: ='[1]Raw Data (Source)'!L55 -> 7588 | E76: ='[1]Raw Data (Source)'!M55 -> 10515 | F76: ='[1]Raw Data (Source)'!N55 -> 15642 | G76: ='[1]Raw Data (Source)'!O55 -> 17541 | H76: ='[1]Raw Data (Source)'!P55 -> 22050
B77: Receivables | C77: ='[1]Raw Data (Source)'!K56 -> -1516 | D77: ='[1]Raw Data (Source)'!L56 -> 4896 | E77: ='[1]Raw Data (Source)'!M56 -> -2506 | F77: ='[1]Raw Data (Source)'!N56 -> -21702 | G77: ='[1]Raw Data (Source)'!O56 -> -21777 | H77: ='[1]Raw Data (Source)'!P56 -> -20952
B78: Inventory | C78: ='[1]Raw Data (Source)'!K57 -> 1316 | D78: ='[1]Raw Data (Source)'!L57 -> 226 | E78: ='[1]Raw Data (Source)'!M57 -> -2173 | F78: ='[1]Raw Data (Source)'!N57 -> -5252 | G78: ='[1]Raw Data (Source)'!O57 -> -1753 | H78: ='[1]Raw Data (Source)'!P57 -> -1646
B79: Payables | C79: ='[1]Raw Data (Source)'!K58 -> -6775 | D79: ='[1]Raw Data (Source)'!L58 -> 7049 | E79: ='[1]Raw Data (Source)'!M58 -> 4972 | F79: ='[1]Raw Data (Source)'!N58 -> 7013 | G79: ='[1]Raw Data (Source)'!O58 -> 4354 | H79: ='[1]Raw Data (Source)'!P58 -> 8485
B80: Loans Advances | C80: ='[1]Raw Data (Source)'!K59 -> 0 | D80: ='[1]Raw Data (Source)'!L59 -> 0 | E80: ='[1]Raw Data (Source)'!M59 -> 0 | F80: ='[1]Raw Data (Source)'!N59 -> 0 | G80: ='[1]Raw Data (Source)'!O59 -> 0 | H80: ='[1]Raw Data (Source)'!P59 -> 0
B81: Other WC items | C81: ='[1]Raw Data (Source)'!K60 -> 0 | D81: ='[1]Raw Data (Source)'!L60 -> 0 | E81: ='[1]Raw Data (Source)'!M60 -> 0 | F81: ='[1]Raw Data (Source)'!N60 -> 0 | G81: ='[1]Raw Data (Source)'!O60 -> 0 | H81: ='[1]Raw Data (Source)'!P60 -> 0
B82: Working capital changes | C82: ='[1]Raw Data (Source)'!K61 -> -6974 | D82: ='[1]Raw Data (Source)'!L61 -> 12171 | E82: ='[1]Raw Data (Source)'!M61 -> 293 | F82: ='[1]Raw Data (Source)'!N61 -> -19941 | G82: ='[1]Raw Data (Source)'!O61 -> -19175 | H82: ='[1]Raw Data (Source)'!P61 -> -14113
B83: Direct taxes | C83: ='[1]Raw Data (Source)'!K62 -> -2257 | D83: ='[1]Raw Data (Source)'!L62 -> -1850 | E83: ='[1]Raw Data (Source)'!M62 -> -1560 | F83: ='[1]Raw Data (Source)'!N62 -> -2775 | G83: ='[1]Raw Data (Source)'!O62 -> -3996 | H83: ='[1]Raw Data (Source)'!P62 -> -4761
B84: Cash from operating Activities | C84: =SUM(C76,C82:C83) -> -1457 | D84: =SUM(D76,D82:D83) -> 17909 | E84: =SUM(E76,E82:E83) -> 9248 | F84: =SUM(F76,F82:F83) -> -7074 | G84: =SUM(G76,G82:G83) -> -5630 | H84: =SUM(H76,H82:H83) -> 3176
B86: Investing Activities
B87: Fixed assets purchased | C87: ='[1]Raw Data (Source)'!K64 -> -6896 | D87: ='[1]Raw Data (Source)'!L64 -> -5989 | E87: ='[1]Raw Data (Source)'!M64 -> -6040 | F87: ='[1]Raw Data (Source)'!N64 -> -6305 | G87: ='[1]Raw Data (Source)'!O64 -> -9946 | H87: ='[1]Raw Data (Source)'!P64 -> -10392
B88: Fixed assets sold | C88: ='[1]Raw Data (Source)'!K65 -> 102 | D88: ='[1]Raw Data (Source)'!L65 -> 1364 | E88: ='[1]Raw Data (Source)'!M65 -> 120 | F88: ='[1]Raw Data (Source)'!N65 -> 138 | G88: ='[1]Raw Data (Source)'!O65 -> 273 | H88: ='[1]Raw Data (Source)'!P65 -> 583
B89: Investments purchased | C89: ='[1]Raw Data (Source)'!K66 -> -198568 | D89: ='[1]Raw Data (Source)'!L66 -> -120055 | E89: ='[1]Raw Data (Source)'!M66 -> -65421 | F89: ='[1]Raw Data (Source)'!N66 -> -50165 | G89: ='[1]Raw Data (Source)'!O66 -> -49927 | H89: ='[1]Raw Data (Source)'!P66 -> -90595
B90: Investments sold | C90: ='[1]Raw Data (Source)'!K67 -> 198132 | D90: ='[1]Raw Data (Source)'!L67 -> 111749 | E90: ='[1]Raw Data (Source)'!M67 -> 65127 | F90: ='[1]Raw Data (Source)'!N67 -> 46269 | G90: ='[1]Raw Data (Source)'!O67 -> 50919 | H90: ='[1]Raw Data (Source)'!P67 -> 85257
B91: Interest received | C91: ='[1]Raw Data (Source)'!K68 -> 372 | D91: ='[1]Raw Data (Source)'!L68 -> 431 | E91: ='[1]Raw Data (Source)'!M68 -> 420 | F91: ='[1]Raw Data (Source)'!N68 -> 464 | G91: ='[1]Raw Data (Source)'!O68 -> 703 | H91: ='[1]Raw Data (Source)'!P68 -> 884
B92: Dividends received | C92: ='[1]Raw Data (Source)'!K69 -> 722 | D92: ='[1]Raw Data (Source)'!L69 -> 577 | E92: ='[1]Raw Data (Source)'!M69 -> 1247 | F92: ='[1]Raw Data (Source)'!N69 -> 1397 | G92: ='[1]Raw Data (Source)'!O69 -> 1213 | H92: ='[1]Raw Data (Source)'!P69 -> 1374
B93: Investment in group cos | C93: ='[1]Raw Data (Source)'!K70 -> -418 | D93: ='[1]Raw Data (Source)'!L70 -> -359 | E93: ='[1]Raw Data (Source)'!M70 -> -222 | F93: ='[1]Raw Data (Source)'!N70 -> -62 | G93: ='[1]Raw Data (Source)'!O70 -> -249 | H93: ='[1]Raw Data (Source)'!P70 -> -29
B94: Issue of shares on acq | C94: ='[1]Raw Data (Source)'!K71 -> 0 | D94: ='[1]Raw Data (Source)'!L71 -> 0 | E94: ='[1]Raw Data (Source)'!M71 -> 0 | F94: ='[1]Raw Data (Source)'!N71 -> 0 | G94: ='[1]Raw Data (Source)'!O71 -> 0 | H94: ='[1]Raw Data (Source)'!P71 -> 0
B95: Redemp n Canc of Shares | C95: ='[1]Raw Data (Source)'!K72 -> 175 | D95: ='[1]Raw Data (Source)'!L72 -> 316 | E95: ='[1]Raw Data (Source)'!M72 -> 617 | F95: ='[1]Raw Data (Source)'!N72 -> 1863 | G95: ='[1]Raw Data (Source)'!O72 -> 1043 | H95: ='[1]Raw Data (Source)'!P72 -> 620
B96: Acquisition of companies | C96: ='[1]Raw Data (Source)'!K73 -> -59 | D96: ='[1]Raw Data (Source)'!L73 -> 0 | E96: ='[1]Raw Data (Source)'!M73 -> -42 | F96: ='[1]Raw Data (Source)'!N73 -> -587 | G96: ='[1]Raw Data (Source)'!O73 -> -53 | H96: ='[1]Raw Data (Source)'!P73 -> 0
B97: Inter corporate deposits | C97: ='[1]Raw Data (Source)'!K74 -> 6 | D97: ='[1]Raw Data (Source)'!L74 -> -262 | E97: ='[1]Raw Data (Source)'!M74 -> -552 | F97: ='[1]Raw Data (Source)'!N74 -> -93 | G97: ='[1]Raw Data (Source)'!O74 -> 485 | H97: ='[1]Raw Data (Source)'!P74 -> -244
B98: Other investing items | C98: ='[1]Raw Data (Source)'!K75 -> -437 | D98: ='[1]Raw Data (Source)'!L75 -> -7457 | E98: ='[1]Raw Data (Source)'!M75 -> 1494 | F98: ='[1]Raw Data (Source)'!N75 -> -1786 | G98: ='[1]Raw Data (Source)'!O75 -> -78 | H98: ='[1]Raw Data (Source)'!P75 -> -6075
B99: Cash from Investing Activities | C99: =SUM(C87:C98) -> -6869 | D99: =SUM(D87:D98) -> -19685 | E99: =SUM(E87:E98) -> -3252 | F99: =SUM(F87:F98) -> -8867 | G99: =SUM(G87:G98) -> -5617 | H99: =SUM(H87:H98) -> -18617
B101: Financing Activities
B102: Proceeds from shares | C102: ='[1]Raw Data (Source)'!K77 -> 1243 | D102: ='[1]Raw Data (Source)'!L77 -> 1 | E102: ='[1]Raw Data (Source)'!M77 -> 1 | F102: ='[1]Raw Data (Source)'!N77 -> 1 | G102: ='[1]Raw Data (Source)'!O77 -> 1 | H102: ='[1]Raw Data (Source)'!P77 -> 1
B103: Proceeds from borrowings | C103: ='[1]Raw Data (Source)'!K78 -> 52618 | D103: ='[1]Raw Data (Source)'!L78 -> 38100 | E103: ='[1]Raw Data (Source)'!M78 -> 53880 | F103: ='[1]Raw Data (Source)'!N78 -> 55622 | G103: ='[1]Raw Data (Source)'!O78 -> 61308 | H103: ='[1]Raw Data (Source)'!P78 -> 82590
B104: Repayment of borrowings | C104: ='[1]Raw Data (Source)'!K79 -> -44044 | D104: ='[1]Raw Data (Source)'!L79 -> -37505 | E104: ='[1]Raw Data (Source)'!M79 -> -57223 | F104: ='[1]Raw Data (Source)'!N79 -> -37056 | G104: ='[1]Raw Data (Source)'!O79 -> -46805 | H104: ='[1]Raw Data (Source)'!P79 -> -64689
B105: Interest paid fin | C105: ='[1]Raw Data (Source)'!K80 -> -624 | D105: ='[1]Raw Data (Source)'!L80 -> -809 | E105: ='[1]Raw Data (Source)'!M80 -> -680 | F105: ='[1]Raw Data (Source)'!N80 -> -734 | G105: ='[1]Raw Data (Source)'!O80 -> -597 | H105: ='[1]Raw Data (Source)'!P80 -> -436
B106: Dividends paid | C106: ='[1]Raw Data (Source)'!K81 -> -1398 | D106: ='[1]Raw Data (Source)'!L81 -> -271 | E106: ='[1]Raw Data (Source)'!M81 -> -1037 | F106: ='[1]Raw Data (Source)'!N81 -> -1522 | G106: ='[1]Raw Data (Source)'!O81 -> -2247 | H106: ='[1]Raw Data (Source)'!P81 -> -2806
B107: Financial liabilities | C107: ='[1]Raw Data (Source)'!K82 -> -558 | D107: ='[1]Raw Data (Source)'!L82 -> -553 | E107: ='[1]Raw Data (Source)'!M82 -> -583 | F107: ='[1]Raw Data (Source)'!N82 -> -751 | G107: ='[1]Raw Data (Source)'!O82 -> -786 | H107: ='[1]Raw Data (Source)'!P82 -> -887
B108: Other financing items | C108: ='[1]Raw Data (Source)'!K83 -> -304 | D108: ='[1]Raw Data (Source)'!L83 -> 1444 | E108: ='[1]Raw Data (Source)'!M83 -> -240 | F108: ='[1]Raw Data (Source)'!N83 -> 386 | G108: ='[1]Raw Data (Source)'!O83 -> 1408 | H108: ='[1]Raw Data (Source)'!P83 -> 2062
B109: Cash from Financing Activities | C109: =SUM(C102:C108) -> 6933 | D109: =SUM(D102:D108) -> 407 | E109: =SUM(E102:E108) -> -5882 | F109: =SUM(F102:F108) -> 15946 | G109: =SUM(G102:G108) -> 12282 | H109: =SUM(H102:H108) -> 15835
B111: Net Cash Flow | C111: =SUM(C84,C99,C109) -> -1393 | D111: =SUM(D84,D99,D109) -> -1369 | E111: =SUM(E84,E99,E109) -> 114 | F111: =SUM(F84,F99,F109) -> 5 | G111: =SUM(G84,G99,G109) -> 1035 | H111: =SUM(H84,H99,H109) -> 394

Sheet Common size statement
B3: Common Size Income Statement - Mahindra and Mahindra Ltd
B5: Particulars | C5: ='[1]Data Sheet'!F16 -> 43921 | D5: ='[1]Data Sheet'!G16 -> 44286 | E5: ='[1]Data Sheet'!H16 -> 44651 | F5: ='[1]Data Sheet'!I16 -> 45016 | G5: ='[1]Data Sheet'!J16 -> 45382 | H5: ='[1]Data Sheet'!K16 -> 45747
B7: ='[1]Data Sheet'!A17 -> Sales | C7: ='[1]Data Sheet'!F17/'[1]Data Sheet'!F$17 -> 1 | D7: ='[1]Data Sheet'!G17/'[1]Data Sheet'!G$17 -> 1 | E7: ='[1]Data Sheet'!H17/'[1]Data Sheet'!H$17 -> 1 | F7: ='[1]Data Sheet'!I17/'[1]Data Sheet'!I$17 -> 1 | G7: ='[1]Data Sheet'!J17/'[1]Data Sheet'!J$17 -> 1 | H7: ='[1]Data Sheet'!K17/'[1]Data Sheet'!K$17 -> 1
B8: ='[1]Data Sheet'!A18 -> Raw Material Cost | C8: ='[1]Data Sheet'!F18/'[1]Data Sheet'!F$17 -> 0.49873093 | D8: ='[1]Data Sheet'!G18/'[1]Data Sheet'!G$17 -> 0.51524426 | E8: ='[1]Data Sheet'!H18/'[1]Data Sheet'!H$17 -> 0.58405808 | F8: ='[1]Data Sheet'!I18/'[1]Data Sheet'!I$17 -> 0.6268721 | G8: ='[1]Data Sheet'!J18/'[1]Data Sheet'!J$17 -> 0.61167046 | H8: ='[1]Data Sheet'!K18/'[1]Data Sheet'!K$17 -> 0.60143463
B9: ='[1]Data Sheet'!A19 -> Change in Inventory | C9: ='[1]Data Sheet'!F19/'[1]Data Sheet'!F$17 -> -0.010965758 | D9: ='[1]Data Sheet'!G19/'[1]Data Sheet'!G$17 -> -0.001825445 | E9: ='[1]Data Sheet'!H19/'[1]Data Sheet'!H$17 -> 0.0095558895 | F9: ='[1]Data Sheet'!I19/'[1]Data Sheet'!I$17 -> 0.016758756 | G9: ='[1]Data Sheet'!J19/'[1]Data Sheet'!J$17 -> 0.010464036 | H9: ='[1]Data Sheet'!K19/'[1]Data Sheet'!K$17 -> 7.6502338e-05
B10: ='[1]Data Sheet'!A20 -> Power and Fuel | C10: ='[1]Data Sheet'!F20/'[1]Data Sheet'!F$17 -> 0.0070430672 | D10: ='[1]Data Sheet'!G20/'[1]Data Sheet'!G$17 -> 0.0057831561 | E10: ='[1]Data Sheet'!H20/'[1]Data Sheet'!H$17 -> 0.0060027346 | F10: ='[1]Data Sheet'!I20/'[1]Data Sheet'!I$17 -> 0.0068482719 | G10: ='[1]Data Sheet'!J20/'[1]Data Sheet'!J$17 -> 0.0054122761 | H10: ='[1]Data Sheet'!K20/'[1]Data Sheet'!K$17 -> 0.0052279738
B11: ='[1]Data Sheet'!A21 -> Other Mfr. Exp | C11: ='[1]Data Sheet'!F21/'[1]Data Sheet'!F$17 -> 0.043482437 | D11: ='[1]Data Sheet'!G21/'[1]Data Sheet'!G$17 -> 0.033972475 | E11: ='[1]Data Sheet'!H21/'[1]Data Sheet'!H$17 -> 0.034648445 | F11: ='[1]Data Sheet'!I21/'[1]Data Sheet'!I$17 -> 0.03165223 | G11: ='[1]Data Sheet'!J21/'[1]Data Sheet'!J$17 -> 0.027263425 | H11: ='[1]Data Sheet'!K21/'[1]Data Sheet'!K$17 -> 0.026143198
B12: ='[1]Data Sheet'!A22 -> Employee Cost | C12: ='[1]Data Sheet'!F22/'[1]Data Sheet'!F$17 -> 0.10897598 | D12: ='[1]Data Sheet'!G22/'[1]Data Sheet'!G$17 -> 0.10518974 | E12: ='[1]Data Sheet'!H22/'[1]Data Sheet'!H$17 -> 0.093009726 | F12: ='[1]Data Sheet'!I22/'[1]Data Sheet'!I$17 -> 0.079805935 | G12: ='[1]Data Sheet'!J22/'[1]Data Sheet'!J$17 -> 0.076391013 | H12: ='[1]Data Sheet'!K22/'[1]Data Sheet'!K$17 -> 0.069883253
B13: ='[1]Data Sheet'!A23 -> Selling and admin | C13: ='[1]Data Sheet'!F23/'[1]Data Sheet'!F$17 -> 0.083793556 | D13: ='[1]Data Sheet'!G23/'[1]Data Sheet'!G$17 -> 0.062316752 | E13: ='[1]Data Sheet'!H23/'[1]Data Sheet'!H$17 -> 0.066292916 | F13: ='[1]Data Sheet'!I23/'[1]Data Sheet'!I$17 -> 0.063345938 | G13: ='[1]Data Sheet'!J23/'[1]Data Sheet'!J$17 -> 0.070695444 | H13: ='[1]Data Sheet'!K23/'[1]Data Sheet'!K$17 -> 0.067906189
B14: ='[1]Data Sheet'!A24 -> Other Expenses | C14: ='[1]Data Sheet'!F24/'[1]Data Sheet'!F$17 -> 0.11225781 | D14: ='[1]Data Sheet'!G24/'[1]Data Sheet'!G$17 -> 0.12101869 | E14: ='[1]Data Sheet'!H24/'[1]Data Sheet'!H$17 -> 0.062709818 | F14: ='[1]Data Sheet'!I24/'[1]Data Sheet'!I$17 -> 0.040958517 | G14: ='[1]Data Sheet'!J24/'[1]Data Sheet'!J$17 -> 0.040053561 | H14: ='[1]Data Sheet'!K24/'[1]Data Sheet'!K$17 -> 0.037797117
B15: ='[1]Data Sheet'!A25 -> Other Income | C15: ='[1]Data Sheet'!F25/'[1]Data Sheet'!F$17 -> 0.011736102 | D15: ='[1]Data Sheet'!G25/'[1]Data Sheet'!G$17 -> 0.015502752 | E15: ='[1]Data Sheet'!H25/'[1]Data Sheet'!H$17 -> 0.03553787 | F15: ='[1]Data Sheet'!I25/'[1]Data Sheet'!I$17 -> 0.032666755 | G15: ='[1]Data Sheet'!J25/'[1]Data Sheet'!J$17 -> 0.023712187 | H15: ='[1]Data Sheet'!K25/'[1]Data Sheet'!K$17 -> 0.023355636
B16: ='[1]Data Sheet'!A26 -> Depreciation | C16: ='[1]Data Sheet'!F26/'[1]Data Sheet'!F$17 -> 0.044661632 | D16: ='[1]Data Sheet'!G26/'[1]Data Sheet'!G$17 -> 0.045479415 | E16: ='[1]Data Sheet'!H26/'[1]Data Sheet'!H$17 -> 0.038898501 | F16: ='[1]Data Sheet'!I26/'[1]Data Sheet'!I$17 -> 0.035926957 | G16: ='[1]Data Sheet'!J26/'[1]Data Sheet'!J$17 -> 0.033964903 | H16: ='[1]Data Sheet'!K26/'[1]Data Sheet'!K$17 -> 0.038148475
B17: ='[1]Data Sheet'!A27 -> Interest | C17: ='[1]Data Sheet'!F27/'[1]Data Sheet'!F$17 -> 0.079875243 | D17: ='[1]Data Sheet'!G27/'[1]Data Sheet'!G$17 -> 0.082154044 | E17: ='[1]Data Sheet'!H27/'[1]Data Sheet'!H$17 -> 0.055650641 | F17: ='[1]Data Sheet'!I27/'[1]Data Sheet'!I$17 -> 0.048072645 | G17: ='[1]Data Sheet'!J27/'[1]Data Sheet'!J$17 -> 0.053841696 | H17: ='[1]Data Sheet'!K27/'[1]Data Sheet'!K$17 -> 0.057052592
B18: ='[1]Data Sheet'!A28 -> Profit before tax | C18: ='[1]Data Sheet'!F28/'[1]Data Sheet'!F$17 -> 0.02194969 | D18: ='[1]Data Sheet'!G28/'[1]Data Sheet'!G$17 -> 0.042518772 | E18: ='[1]Data Sheet'!H28/'[1]Data Sheet'!H$17 -> 0.1038229 | F18: ='[1]Data Sheet'!I28/'[1]Data Sheet'!I$17 -> 0.11594292 | G18: ='[1]Data Sheet'!J28/'[1]Data Sheet'!J$17 -> 0.11488344 | H18: ='[1]Data Sheet'!K28/'[1]Data Sheet'!K$17 -> 0.11983871
... B21: ='[1]Data Sheet'!A31 -> Dividend Amount | C21: ='[1]Data Sheet'!F31/'[1]Data Sheet'!F$17 -> 0.003455868 | D21: ='[1]Data Sheet'!G31/'[1]Data Sheet'!G$17 -> 0.013079416 | E21: ='[1]Data Sheet'!H31/'[1]Data Sheet'!H$17 -> 0.014245224 | F21: ='[1]Data Sheet'!I31/'[1]Data Sheet'!I$17 -> 0.014922748 | G21: ='[1]Data Sheet'!J31/'[1]Data Sheet'!J$17 -> 0.016912347 | H21: ='[1]Data Sheet'!K31/'[1]Data Sheet'!K$17 -> 0.017738995
B22: ='[1]Data Sheet'!A34 -> EBITDA | C22: ='[1]Data Sheet'!F34/'[1]Data Sheet'!F$17 -> 0.15243016 | D22: ='[1]Data Sheet'!G34/'[1]Data Sheet'!G$17 -> 0.17419247 | E22: ='[1]Data Sheet'!H34/'[1]Data Sheet'!H$17 -> 0.19087858 | F22: ='[1]Data Sheet'!I34/'[1]Data Sheet'!I$17 -> 0.19092964 | G22: ='[1]Data Sheet'!J34/'[1]Data Sheet'!J$17 -> 0.19549136 | H22: ='[1]Data Sheet'!K34/'[1]Data Sheet'!K$17 -> 0.2078539
B24: Common Size Balance Sheet - Mahindra and Mahindra Ltd
B26: =B5 -> Particulars | C26: =C5 -> 43921 | D26: =D5 -> 44286 | E26: =E5 -> 44651 | F26: =F5 -> 45016 | G26: =G5 -> 45382 | H26: =H5 -> 45747
B28: Total liabilities | C28: ='[1]Data Sheet'!F61/'[1]Data Sheet'!F$61 -> 1 | D28: ='[1]Data Sheet'!G61/'[1]Data Sheet'!G$61 -> 1 | E28: ='[1]Data Sheet'!H61/'[1]Data Sheet'!H$61 -> 1 | F28: ='[1]Data Sheet'!I61/'[1]Data Sheet'!I$61 -> 1 | G28: ='[1]Data Sheet'!J61/'[1]Data Sheet'!J$61 -> 1 | H28: ='[1]Data Sheet'!K61/'[1]Data Sheet'!K$61 -> 1
B29: ='[1]Data Sheet'!A57 -> Equity Share Capital | C29: ='[1]Data Sheet'!F57/'[1]Data Sheet'!F$61 -> 0.0033447559 | D29: ='[1]Data Sheet'!G57/'[1]Data Sheet'!G$61 -> 0.0033651914 | E29: ='[1]Data Sheet'!H57/'[1]Data Sheet'!H$61 -> 0.0032256214 | F29: ='[1]Data Sheet'!I57/'[1]Data Sheet'!I$61 -> 0.0027257268 | G29: ='[1]Data Sheet'!J57/'[1]Data Sheet'!J$61 -> 0.0023746416 | H29: ='[1]Data Sheet'!K57/'[1]Data Sheet'!K$61 -> 0.0020221862
B30: ='[1]Data Sheet'!A58 -> Reserves | C30: ='[1]Data Sheet'!F58/'[1]Data Sheet'!F$61 -> 0.23784667 | D30: ='[1]Data Sheet'!G58/'[1]Data Sheet'!G$61 -> 0.24869483 | E30: ='[1]Data Sheet'!H58/'[1]Data Sheet'!H$61 -> 0.27012581 | F30: ='[1]Data Sheet'!I58/'[1]Data Sheet'!I$61 -> 0.27319422 | G30: ='[1]Data Sheet'!J58/'[1]Data Sheet'!J$61 -> 0.27962118 | H30: ='[1]Data Sheet'!K58/'[1]Data Sheet'!K$61 -> 0.27709081
B31: ='[1]Data Sheet'!A59 -> Borrowings | C31: ='[1]Data Sheet'!F59/'[1]Data Sheet'!F$61 -> 0.49537894 | D31: ='[1]Data Sheet'!G59/'[1]Data Sheet'!G$61 -> 0.48872914 | E31: ='[1]Data Sheet'!H59/'[1]Data Sheet'!H$61 -> 0.45017628 | F31: ='[1]Data Sheet'!I59/'[1]Data Sheet'!I$61 -> 0.45156372 | G31: ='[1]Data Sheet'!J59/'[1]Data Sheet'!J$61 -> 0.46287681 | H31: ='[1]Data Sheet'!K59/'[1]Data Sheet'!K$61 -> 0.46745807
B32: ='[1]Data Sheet'!A60 -> Other Liabilities | C32: ='[1]Data Sheet'!F60/'[1]Data Sheet'!F$61 -> 0.26342964 | D32: ='[1]Data Sheet'!G60/'[1]Data Sheet'!G$61 -> 0.25921084 | E32: ='[1]Data Sheet'!H60/'[1]Data Sheet'!H$61 -> 0.27647229 | F32: ='[1]Data Sheet'!I60/'[1]Data Sheet'!I$61 -> 0.27251634 | G32: ='[1]Data Sheet'!J60/'[1]Data Sheet'!J$61 -> 0.25512737 | H32: ='[1]Data Sheet'!K60/'[1]Data Sheet'!K$61 -> 0.25342893
B34: Total Assets | C34: ='[1]Data Sheet'!F76/'[1]Data Sheet'!F$76 -> 1 | D34: ='[1]Data Sheet'!G76/'[1]Data Sheet'!G$76 -> 1 | E34: ='[1]Data Sheet'!H76/'[1]Data Sheet'!H$76 -> 1 | F34: ='[1]Data Sheet'!I76/'[1]Data Sheet'!I$76 -> 1 | G34: ='[1]Data Sheet'!J76/'[1]Data Sheet'!J$76 -> 1 | H34: ='[1]Data Sheet'!K76/'[1]Data Sheet'!K$76 -> 1
B35: ='[1]Data Sheet'!A62 -> Net Block | C35: ='[1]Data Sheet'!F62/'[1]Data Sheet'!F$76 -> 0.17915739 | D35: ='[1]Data Sheet'!G62/'[1]Data Sheet'!G$76 -> 0.12959869 | E35: ='[1]Data Sheet'!H62/'[1]Data Sheet'!H$76 -> 0.15092939 | F35: ='[1]Data Sheet'!I62/'[1]Data Sheet'!I$76 -> 0.13285473 | G35: ='[1]Data Sheet'!J62/'[1]Data Sheet'!J$76 -> 0.11984152 | H35: ='[1]Data Sheet'!K62/'[1]Data Sheet'!K$76 -> 0.12548807
B36: ='[1]Data Sheet'!A63 -> Capital Work in Progress | C36: ='[1]Data Sheet'!F63/'[1]Data Sheet'!F$76 -> 0.04137485 | D36: ='[1]Data Sheet'!G63/'[1]Data Sheet'!G$76 -> 0.047721948 | E36: ='[1]Data Sheet'!H63/'[1]Data Sheet'!H$76 -> 0.038882004 | F36: ='[1]Data Sheet'!I63/'[1]Data Sheet'!I$76 -> 0.019426861 | G36: ='[1]Data Sheet'!J63/'[1]Data Sheet'!J$76 -> 0.034250343 | H36: ='[1]Data Sheet'!K63/'[1]Data Sheet'!K$76 -> 0.03006248
B37: ='[1]Data Sheet'!A64 -> Investments | C37: ='[1]Data Sheet'!F64/'[1]Data Sheet'!F$76 -> 0.11592318 | D37: ='[1]Data Sheet'!G64/'[1]Data Sheet'!G$76 -> 0.17444354 | E37: ='[1]Data Sheet'!H64/'[1]Data Sheet'!H$76 -> 0.17437609 | F37: ='[1]Data Sheet'!I64/'[1]Data Sheet'!I$76 -> 0.17266438 | G37: ='[1]Data Sheet'!J64/'[1]Data Sheet'!J$76 -> 0.14999931 | H37: ='[1]Data Sheet'!K64/'[1]Data Sheet'!K$76 -> 0.1496616
B38: ='[1]Data Sheet'!A65 -> Other Assets | C38: ='[1]Data Sheet'!F75/'[1]Data Sheet'!F$76 -> 0.50694522 | D38: ='[1]Data Sheet'!G75/'[1]Data Sheet'!G$76 -> 0.47562596 | E38: ='[1]Data Sheet'!H75/'[1]Data Sheet'!H$76 -> 0.46708095 | F38: ='[1]Data Sheet'!I75/'[1]Data Sheet'!I$76 -> 0.50295749 | G38: ='[1]Data Sheet'!J75/'[1]Data Sheet'!J$76 -> 0.53374822 | H38: ='[1]Data Sheet'!K75/'[1]Data Sheet'!K$76 -> 0.5164432
B39: ='[1]Data Sheet'!A67 -> Receivables | C39: ='[1]Data Sheet'!F67/'[1]Data Sheet'!F$76 -> 0.041808121 | D39: ='[1]Data Sheet'!G67/'[1]Data Sheet'!G$76 -> 0.036417657 | E39: ='[1]Data Sheet'!H67/'[1]Data Sheet'!H$76 -> 0.036974336 | F39: ='[1]Data Sheet'!I67/'[1]Data Sheet'!I$76 -> 0.03440333 | G39: ='[1]Data Sheet'!J67/'[1]Data Sheet'!J$76 -> 0.031779758 | H39: ='[1]Data Sheet'!K67/'[1]Data Sheet'!K$76 -> 0.029997483
B40: ='[1]Data Sheet'!A68 -> Inventory | C40: ='[1]Data Sheet'!F68/'[1]Data Sheet'!F$76 -> 0.067053581 | D40: ='[1]Data Sheet'!G68/'[1]Data Sheet'!G$76 -> 0.0582864 | E40: ='[1]Data Sheet'!H68/'[1]Data Sheet'!H$76 -> 0.067265628 | F40: ='[1]Data Sheet'!I68/'[1]Data Sheet'!I$76 -> 0.08250789 | G40: ='[1]Data Sheet'!J68/'[1]Data Sheet'!J$76 -> 0.079202165 | H40: ='[1]Data Sheet'!K68/'[1]Data Sheet'!K$76 -> 0.073659278
B41: ='[1]Data Sheet'!A69 -> Cash & Bank | C41: ='[1]Data Sheet'!F69/'[1]Data Sheet'!F$76 -> 0.047737658 | D41: ='[1]Data Sheet'!G69/'[1]Data Sheet'!G$76 -> 0.077905802 | E41: ='[1]Data Sheet'!H69/'[1]Data Sheet'!H$76 -> 0.064491603 | F41: ='[1]Data Sheet'!I69/'[1]Data Sheet'!I$76 -> 0.05518532 | G41: ='[1]Data Sheet'!J69/'[1]Data Sheet'!J$76 -> 0.051178685 | H41: ='[1]Data Sheet'!K69/'[1]Data Sheet'!K$76 -> 0.074687888

Sheet Ratio Analysis
B2: Ratio Analysis - Mahindra and Mahindra Ltd
B3: Years | C3: 43921 | D3: 44286 | E3: 44651 | F3: 45016 | G3: 45382 | H3: 45747 | I3: Trend | J3: Mean | K3: Median
B5: SalesGrowth | D5: ='M&M PROJECT 3 Statement'!D11 -> -0.01464741 | E5: ='M&M PROJECT 3 Statement'!E11 -> 0.21396426 | F5: ='M&M PROJECT 3 Statement'!F11 -> 0.34487949 | G5: ='M&M PROJECT 3 Statement'!G11 -> 0.14686182 | H5: ='M&M PROJECT 3 Statement'!H11 -> 0.14475698 | J5: =AVERAGE(D5:H5) -> 0.16716303 | K5: =MEDIAN(C5:H5) -> 0.14686182
B6: EBITDA Growth | D6: ='M&M PROJECT 3 Statement'!D22/'M&M PROJECT 3 Statement'!C22-1 -> 0.13086264 | E6: ='M&M PROJECT 3 Statement'!E22/'M&M PROJECT 3 Statement'!D22-1 -> 0.27821228 | F6: ='M&M PROJECT 3 Statement'!F22/'M&M PROJECT 3 Statement'!E22-1 -> 0.38156352 | G6: ='M&M PROJECT 3 Statement'!G22/'M&M PROJECT 3 Statement'!F22-1 -> 0.22709264 | H6: ='M&M PROJECT 3 Statement'!H22/'M&M PROJECT 3 Statement'!G22-1 -> 0.22602747 | J6: =AVERAGE(D6:H6) -> 0.24875171 | K6: =MEDIAN(C6:H6) -> 0.22709264
B7: EBIT Growth | D7: ='M&M PROJECT 3 Statement'!D31/'M&M PROJECT 3 Statement'!C31-1 -> 1.6063617 | E7: ='M&M PROJECT 3 Statement'!E31/'M&M PROJECT 3 Statement'!D31-1 -> 2.0683862 | F7: ='M&M PROJECT 3 Statement'!F31/'M&M PROJECT 3 Statement'!E31-1 -> 0.64013123 | G7: ='M&M PROJECT 3 Statement'!G31/'M&M PROJECT 3 Statement'!F31-1 -> 0.25559127 | H7: ='M&M PROJECT 3 Statement'!H31/'M&M PROJECT 3 Statement'!G31-1 -> 0.21145289 | J7: =AVERAGE(D7:H7) -> 0.95638467 | K7: =MEDIAN(C7:H7) -> 0.64013123
B8: Net Profit Growth | D8: ='M&M PROJECT 3 Statement'!D40/'M&M PROJECT 3 Statement'!C40-1 -> -5.7114953 | E8: ='M&M PROJECT 3 Statement'!E40/'M&M PROJECT 3 Statement'!D40-1 -> 3.7957273 | F8: ='M&M PROJECT 3 Statement'!F40/'M&M PROJECT 3 Statement'!E40-1 -> 0.5682427 | G8: ='M&M PROJECT 3 Statement'!G40/'M&M PROJECT 3 Statement'!F40-1 -> 0.078714807 | H8: ='M&M PROJECT 3 Statement'!H40/'M&M PROJECT 3 Statement'!G40-1 -> 0.14697445 | J8: =AVERAGE(D8:H8) -> -0.22436722 | K8: =MEDIAN(C8:H8) -> 0.14697445
B9: Dividend Growth | D9: ='M&M PROJECT 3 Statement'!D48/'M&M PROJECT 3 Statement'!C48-1 -> 2.7292618 | E9: ='M&M PROJECT 3 Statement'!E48/'M&M PROJECT 3 Statement'!D48-1 -> 0.32216858 | F9: ='M&M PROJECT 3 Statement'!F48/'M&M PROJECT 3 Statement'!E48-1 -> 0.40850402 | G9: ='M&M PROJECT 3 Statement'!G48/'M&M PROJECT 3 Statement'!F48-1 -> 0.29976902 | H9: ='M&M PROJECT 3 Statement'!H48/'M&M PROJECT 3 Statement'!G48-1 -> 0.20071084 | J9: =AVERAGE(D9:H9) -> 0.79208286 | K9: =MEDIAN(C9:H9) -> 0.32216858
B11: Gross Margin | C11: ='M&M PROJECT 3 Statement'!C17 -> 0.33080182 | D11: ='M&M PROJECT 3 Statement'!D17 -> 0.33798493 | E11: ='M&M PROJECT 3 Statement'!E17 -> 0.2918369 | F11: ='M&M PROJECT 3 Statement'!F17 -> 0.27158022 | G11: ='M&M PROJECT 3 Statement'!G17 -> 0.28972686 | H11: ='M&M PROJECT 3 Statement'!H17 -> 0.29738745 | J11: =AVERAGE(C11:H11) -> 0.3032197 | K11: =MEDIAN(C11:H11) -> 0.29461218
B12: EBITDA Margin | C12: ='M&M PROJECT 3 Statement'!C23 -> 0.13475046 | D12: ='M&M PROJECT 3 Statement'!D23 -> 0.15464948 | E12: ='M&M PROJECT 3 Statement'!E23 -> 0.16283417 | F12: ='M&M PROJECT 3 Statement'!F23 -> 0.16727577 | G12: ='M&M PROJECT 3 Statement'!G23 -> 0.17897785 | H12: ='M&M PROJECT 3 Statement'!H23 -> 0.19168415 | J12: =AVERAGE(C12:H12) -> 0.16502865 | K12: =MEDIAN(C12:H12) -> 0.16505497
B13: EBIT Margin | C13: 0.090088832 | D13: 0.10917006 | E13: 0.12393567 | F13: 0.13134881 | G13: 0.14501295 | H13: 0.15353567 | J13: =AVERAGE(C13:H13) -> 0.12551533 | K13: =MEDIAN(C13:H13) -> 0.12764224
B14: EBT Margin | C14: ='M&M PROJECT 3 Statement'!C32 -> 0.010213588 | D14: ='M&M PROJECT 3 Statement'!D32 -> 0.02701602 | E14: ='M&M PROJECT 3 Statement'!E32 -> 0.068285029 | F14: ='M&M PROJECT 3 Statement'!F32 -> 0.083276167 | G14: ='M&M PROJECT 3 Statement'!G32 -> 0.091171252 | H14: ='M&M PROJECT 3 Statement'!H32 -> 0.096483078 | J14: =AVERAGE(C14:H14) -> 0.062740856 | K14: =MEDIAN(C14:H14) -> 0.075780598
B15: Net Profit Margin | C15: ='M&M PROJECT 3 Statement'!C41 -> -0.004258315 | D15: ='M&M PROJECT 3 Statement'!D41 -> 0.020361271 | E15: ='M&M PROJECT 3 Statement'!E41 -> 0.080436555 | F15: ='M&M PROJECT 3 Statement'!F41 -> 0.093795795 | G15: ='M&M PROJECT 3 Statement'!G41 -> 0.088222409 | H15: ='M&M PROJECT 3 Statement'!H41 -> 0.088393301 | J15: =AVERAGE(C15:H15) -> 0.061158503 | K15: =MEDIAN(C15:H15) -> 0.084329482
B17: SalesExpenses%Sales | C17: ='M&M PROJECT 3 Statement'!C20 -> 0.19605136 | D17: ='M&M PROJECT 3 Statement'!D20 -> 0.18333545 | E17: ='M&M PROJECT 3 Statement'!E20 -> 0.12900273 | F17: ='M&M PROJECT 3 Statement'!F20 -> 0.10430445 | G17: ='M&M PROJECT 3 Statement'!G20 -> 0.110749 | H17: ='M&M PROJECT 3 Statement'!H20 -> 0.10570331 | J17: =AVERAGE(C17:H17) -> 0.13819105 | K17: =MEDIAN(C17:H17) -> 0.11987587
B18: Depreciation%Sales | C18: ='M&M PROJECT 3 Statement'!C29 -> 0.044661632 | D18: ='M&M PROJECT 3 Statement'!D29 -> 0.045479415 | E18: ='M&M PROJECT 3 Statement'!E29 -> 0.038898501 | F18: ='M&M PROJECT 3 Statement'!F29 -> 0.035926957 | G18: ='M&M PROJECT 3 Statement'!G29 -> 0.033964903 | H18: ='M&M PROJECT 3 Statement'!H29 -> 0.038148475 | J18: =AVERAGE(C18:H18) -> 0.039513314 | K18: =MEDIAN(C18:H18) -> 0.038523488
B19: OperatingIncome%Sales | C19: ='Ratio Analysis'!C13 -> 0.090088832 | D19: ='Ratio Analysis'!D13 -> 0.10917006 | E19: ='Ratio Analysis'!E13 -> 0.12393567 | F19: ='Ratio Analysis'!F13 -> 0.13134881 | G19: ='Ratio Analysis'!G13 -> 0.14501295 | H19: ='Ratio Analysis'!H13 -> 0.15353567 | J19: =AVERAGE(C19:H19) -> 0.12551533 | K19: =MEDIAN(C19:H19) -> 0.12764224
B21: Return on Capital Employed | C21: =('M&M PROJECT 3 Statement'!C22-'M&M PROJECT 3 Statement'!C28)/(SUM('M&M PROJECT 3 Statement'!C53:C55)) -> 0.055636421 | D21: =('M&M PROJECT 3 Statement'!D22-'M&M PROJECT 3 Statement'!D28)/(SUM('M&M PROJECT 3 Statement'!D53:D55)) -> 0.066354027 | E21: =('M&M PROJECT 3 Statement'!E22-'M&M PROJECT 3 Statement'!E28)/(SUM('M&M PROJECT 3 Statement'!E53:E55)) -> 0.089597872 | F21: =('M&M PROJECT 3 Statement'!F22-'M&M PROJECT 3 Statement'!F28)/(SUM('M&M PROJECT 3 Statement'!F53:F55)) -> 0.10718119 | G21: =('M&M PROJECT 3 Statement'!G22-'M&M PROJECT 3 Statement'!G28)/(SUM('M&M PROJECT 3 Statement'!G53:G55)) -> 0.11535349 | H21: =('M&M PROJECT 3 Statement'!H22-'M&M PROJECT 3 Statement'!H28)/(SUM('M&M PROJECT 3 Statement'!H53:H55)) -> 0.11862628 | J21: =AVERAGE(C21:H21) -> 0.092124881 | K21: =MEDIAN(C21:H21) -> 0.098389533
B22: Return on Equity% | C22: =('M&M PROJECT 3 Statement'!C40)/(SUM('M&M PROJECT 3 Statement'!C53:C54)) -> -0.0080311619 | D22: =('M&M PROJECT 3 Statement'!D40)/(SUM('M&M PROJECT 3 Statement'!D53:D54)) -> 0.036371336 | E22: =('M&M PROJECT 3 Statement'!E40)/(SUM('M&M PROJECT 3 Statement'!E53:E54)) -> 0.15391773 | F22: =('M&M PROJECT 3 Statement'!F40)/(SUM('M&M PROJECT 3 Statement'!F53:F54)) -> 0.20179758 | G22: =('M&M PROJECT 3 Statement'!G40)/(SUM('M&M PROJECT 3 Statement'!G53:G54)) -> 0.18537117 | H22: =('M&M PROJECT 3 Statement'!H40)/(SUM('M&M PROJECT 3 Statement'!H53:H54)) -> 0.18267625 | J22: =AVERAGE(C22:H22) -> 0.12535049 | K22: =MEDIAN(C22:H22) -> 0.16829699
B23: Interest Coverage Ratio | C23: =('M&M PROJECT 3 Statement'!C22-'M&M PROJECT 3 Statement'!C28)/('M&M PROJECT 3 Statement'!C25) -> 1.1278693 | D23: =('M&M PROJECT 3 Statement'!D22-'M&M PROJECT 3 Statement'!D28)/('M&M PROJECT 3 Statement'!D25) -> 1.3288459 | E23: =('M&M PROJECT 3 Statement'!E22-'M&M PROJECT 3 Statement'!E28)/('M&M PROJECT 3 Statement'!E25) -> 2.2270304 | F23: =('M&M PROJECT 3 Statement'!F22-'M&M PROJECT 3 Statement'!F28)/('M&M PROJECT 3 Statement'!F25) -> 2.7322984 | G23: =('M&M PROJECT 3 Statement'!G22-'M&M PROJECT 3 Statement'!G28)/('M&M PROJECT 3 Statement'!G25) -> 2.6933206 | H23: =('M&M PROJECT 3 Statement'!H22-'M&M PROJECT 3 Statement'!H28)/('M&M PROJECT 3 Statement'!H25) -> 2.6911252 | J23: =AVERAGE(C23:H23) -> 2.133415 | K23: =MEDIAN(C23:H23) -> 2.4590778
B25: Debtor Turnover Ratio | C25: ='M&M PROJECT 3 Statement'!C10/'M&M PROJECT 3 Statement'!C65 -> 10.880324 | D25: ='M&M PROJECT 3 Statement'!D10/'M&M PROJECT 3 Statement'!D65 -> 12.36364 | E25: ='M&M PROJECT 3 Statement'!E10/'M&M PROJECT 3 Statement'!E65 -> 14.146733 | F25: ='M&M PROJECT 3 Statement'!F10/'M&M PROJECT 3 Statement'!F65 -> 17.255009 | G25: ='M&M PROJECT 3 Statement'!G10/'M&M PROJECT 3 Statement'!G65 -> 18.644699 | H25: ='M&M PROJECT 3 Statement'!H10/'M&M PROJECT 3 Statement'!H65 -> 19.229057 | J25: =AVERAGE(C25:H25) -> 15.41991 | K25: =MEDIAN(C25:H25) -> 15.700871
B26: Creditor Turnover Ratio | C26: ='M&M PROJECT 3 Statement'!C10/'M&M PROJECT 3 Statement'!C56 -> 1.7267833 | D26: ='M&M PROJECT 3 Statement'!D10/'M&M PROJECT 3 Statement'!D56 -> 1.7370214 | E26: ='M&M PROJECT 3 Statement'!E10/'M&M PROJECT 3 Statement'!E56 -> 1.8919295 | F26: ='M&M PROJECT 3 Statement'!F10/'M&M PROJECT 3 Statement'!F56 -> 2.1783273 | G26: ='M&M PROJECT 3 Statement'!G10/'M&M PROJECT 3 Statement'!G56 -> 2.3224636 | H26: ='M&M PROJECT 3 Statement'!H10/'M&M PROJECT 3 Statement'!H56 -> 2.2760752 | J26: =AVERAGE(C26:H26) -> 2.0221 | K26: =MEDIAN(C26:H26) -> 2.0351284
B27: Inventory Turnover | C27: ='M&M PROJECT 3 Statement'!C10/'M&M PROJECT 3 Statement'!C66 -> 6.7839165 | D27: ='M&M PROJECT 3 Statement'!D10/'M&M PROJECT 3 Statement'!D66 -> 7.7248687 | E27: ='M&M PROJECT 3 Statement'!E10/'M&M PROJECT 3 Statement'!E66 -> 7.7761271 | F27: ='M&M PROJECT 3 Statement'!F10/'M&M PROJECT 3 Statement'!F66 -> 7.1948244 | G27: ='M&M PROJECT 3 Statement'!G10/'M&M PROJECT 3 Statement'!G66 -> 7.4811594 | H27: ='M&M PROJECT 3 Statement'!H10/'M&M PROJECT 3 Statement'!H66 -> 7.8309659 | J27: =AVERAGE(C27:H27) -> 7.4653103 | K27: =MEDIAN(C27:H27) -> 7.6030141
B28: Fixed Asset Turnover | C28: ='M&M PROJECT 3 Statement'!C10/'M&M PROJECT 3 Statement'!C59 -> 2.5390294 | D28: ='M&M PROJECT 3 Statement'!D10/'M&M PROJECT 3 Statement'!D59 -> 3.4742232 | E28: ='M&M PROJECT 3 Statement'!E10/'M&M PROJECT 3 Statement'!E59 -> 3.4656342 | F28: ='M&M PROJECT 3 Statement'!F10/'M&M PROJECT 3 Statement'!F59 -> 4.4682623 | G28: ='M&M PROJECT 3 Statement'!G10/'M&M PROJECT 3 Statement'!G59 -> 4.9442299 | H28: ='M&M PROJECT 3 Statement'!H10/'M&M PROJECT 3 Statement'!H59 -> 4.5966383 | J28: =AVERAGE(C28:H28) -> 3.9146696 | K28: =MEDIAN(C28:H28) -> 3.9712428
B29: Capital Turnover Ratio | C29: =('M&M PROJECT 3 Statement'!C10)/(SUM('M&M PROJECT 3 Statement'!C53:C54)) -> 1.8859953 | D29: =('M&M PROJECT 3 Statement'!D10)/(SUM('M&M PROJECT 3 Statement'!D53:D54)) -> 1.7862999 | E29: =('M&M PROJECT 3 Statement'!E10)/(SUM('M&M PROJECT 3 Statement'!E53:E54)) -> 1.9135297 | F29: =('M&M PROJECT 3 Statement'!F10)/(SUM('M&M PROJECT 3 Statement'!F53:F54)) -> 2.1514566 | G29: =('M&M PROJECT 3 Statement'!G10)/(SUM('M&M PROJECT 3 Statement'!G53:G54)) -> 2.1011802 | H29: =('M&M PROJECT 3 Statement'!H10)/(SUM('M&M PROJECT 3 Statement'!H53:H54)) -> 2.06663 | J29: =AVERAGE(C29:H29) -> 1.9841819 | K29: =MEDIAN(C29:H29) -> 1.9900798
B31: Debtor Days | C31: =365/C25 -> 33.546796 | D31: =365/D25 -> 29.522051 | E31: =365/E25 -> 25.80101 | F31: =365/F25 -> 21.153278 | G31: =365/G25 -> 19.57661 | H31: =365/H25 -> 18.98169 | J31: =AVERAGE(C31:H31) -> 24.763572 | K31: =MEDIAN(C31:H31) -> 23.477144
B32: Payable Days | C32: =365/C26 -> 211.37569 | D32: =365/D26 -> 210.12982 | E32: =365/E26 -> 192.92474 | F32: =365/F26 -> 167.55976 | G32: =365/G26 -> 157.1607 | H32: =365/H26 -> 160.36377 | J32: =AVERAGE(C32:H32) -> 183.25241 | K32: =MEDIAN(C32:H32) -> 180.24225
B33: Inventory Days | C33: =365/C27 -> 53.803729 | D33: =365/D27 -> 47.249994 | E33: =365/E27 -> 46.938533 | F33: =365/F27 -> 50.730911 | G33: =365/G27 -> 48.789229 | H33: =365/H27 -> 46.609831 | J33: =AVERAGE(C33:H33) -> 49.020371 | K33: =MEDIAN(C33:H33) -> 48.019611
B34: Cash Conversion Cycle (in days) | C34: =SUM(C31,C33)-C32 -> -124.02516 | D34: =SUM(D31,D33)-D32 -> -133.35778 | E34: =SUM(E31,E33)-E32 -> -120.1852 | F34: =SUM(F31,F33)-F32 -> -95.675569 | G34: =SUM(G31,G33)-G32 -> -88.79486 | H34: =SUM(H31,H33)-H32 -> -94.772251 | J34: =AVERAGE(C34:H34) -> -109.46847 | K34: =MEDIAN(C34:H34) -> -107.93038
B36: CFO/Sales | C36: ='M&M PROJECT 3 Statement'!C84/'M&M PROJECT 3 Statement'!C10 -> -0.01932824 | D36: ='M&M PROJECT 3 Statement'!D84/'M&M PROJECT 3 Statement'!D10 -> 0.24110844 | E36: ='M&M PROJECT 3 Statement'!E84/'M&M PROJECT 3 Statement'!E10 -> 0.10256118 | F36: ='M&M PROJECT 3 Statement'!F84/'M&M PROJECT 3 Statement'!F10 -> -0.058333344 | G36: ='M&M PROJECT 3 Statement'!G84/'M&M PROJECT 3 Statement'!G10 -> -0.040480803 | H36: ='M&M PROJECT 3 Statement'!H84/'M&M PROJECT 3 Statement'!H10 -> 0.019948393 | J36: =AVERAGE(C36:H36) -> 0.040912605 | K36: =MEDIAN(C36:H36) -> 0.00031007671
B37: CFO/Total Assets | C37: ='M&M PROJECT 3 Statement'!C84/'M&M PROJECT 3 Statement'!C70 -> -0.0087921435 | D37: ='M&M PROJECT 3 Statement'!D84/'M&M PROJECT 3 Statement'!D70 -> 0.10856023 | E37: ='M&M PROJECT 3 Statement'!E84/'M&M PROJECT 3 Statement'!E70 -> 0.053646273 | F37: ='M&M PROJECT 3 Statement'!F84/'M&M PROJECT 3 Statement'!F70 -> -0.03462841 | G37: ='M&M PROJECT 3 Statement'!G84/'M&M PROJECT 3 Statement'!G70 -> -0.023985848 | H37: ='M&M PROJECT 3 Statement'!H84/'M&M PROJECT 3 Statement'!H70 -> 0.011506698 | J37: =AVERAGE(C37:H37) -> 0.0177178 | K37: =MEDIAN(C37:H37) -> 0.0013572771
B38: CFO/Total Debt | C38: ='M&M PROJECT 3 Statement'!C84/'M&M PROJECT 3 Statement'!C55 -> -0.017748319 | D38: ='M&M PROJECT 3 Statement'!D84/'M&M PROJECT 3 Statement'!D55 -> 0.2221276 | E38: ='M&M PROJECT 3 Statement'!E84/'M&M PROJECT 3 Statement'!E55 -> 0.11916726 | F38: ='M&M PROJECT 3 Statement'!F84/'M&M PROJECT 3 Statement'!F55 -> -0.076685545 | G38: ='M&M PROJECT 3 Statement'!G84/'M&M PROJECT 3 Statement'!G55 -> -0.051819075 | H38: ='M&M PROJECT 3 Statement'!H84/'M&M PROJECT 3 Statement'!H55 -> 0.024615465 | J38: =AVERAGE(C38:H38) -> 0.036609564 | K38: =MEDIAN(C38:H38) -> 0.0034335727

Sheet DCF (WACC)
B2: MAHINDRA AND MAHINDRA LTD PROJECT
B5: Weighted Average Cost of Capital
B7: All figures are in INR unless stated otherwise.
B10: Peer comps
G11: Debt / | H11: Debt / | I11: Levered | J11: Unlevered
B12: Name of the comps | C12: Country | D12: Total Debt | E12: Total Equity | F12: Tax Rate 1 | G12: Equity | H12: Capital | I12: Beta 2 | J12: Beta 3
B14: Tata Motors Ltd. | C14: India | D14: 8608 | E14: 33442 | F14: 0.2517 | G14: =D14/E14 -> 0.25740087 | H14: =D14/(D14+E14) -> 0.20470868 | I14: 1.15 | J14: =(I14/(1+(1-F14)*G14)) -> 0.96426915
B15: Maruti Suzuki India | C15: India | D15: 33.1 | E15: 94046.7 | F15: 0.2517 | G15: =D15/E15 -> 0.00035195281 | H15: =D15/(D15+E15) -> 0.00035182898 | I15: 0.85 | J15: =(I15/(1+(1-F15)*G15)) -> 0.8497762
B16: Bajaj Auto Ltd. | C16: India | D16: 784 | E16: 30400 | F16: 0.2517 | G16: =D16/E16 -> 0.025789474 | H16: =D16/(D16+E16) -> 0.025141098 | I16: 0.88 | J16: =(I16/(1+(1-F16)*G16)) -> 0.86333906
B17: Hero MotoCorp Ltd. | C17: India | D17: 699.9 | E17: 19272 | F17: 0.2517 | G17: =D17/E17 -> 0.036316936 | H17: =D17/(D17+E17) -> 0.035044237 | I17: 0.72 | J17: =(I17/(1+(1-F17)*G17)) -> 0.70095098
B18: Eicher Motors Ltd. | C18: India | D18: 266.5 | E18: 21296.5 | F18: 0.2517 | G18: =D18/E18 -> 0.012513793 | H18: =D18/(D18+E18) -> 0.012359134 | I18: 0.78 | J18: =(I18/(1+(1-F18)*G18)) -> 0.77276378
E20: Average | F20: =AVERAGE(F14:F18) -> 0.2517 | G20: =AVERAGE(G14:G18) -> 0.066474606 | H20: =AVERAGE(H14:H18) -> 0.055520996 | I20: =AVERAGE(I14:I18) -> 0.876 | J20: =AVERAGE(J14:J18) -> 0.83021983
E21: Median | F21: =MEDIAN(F14:F18) -> 0.2517 | G21: =MEDIAN(G14:G18) -> 0.025789474 | H21: =MEDIAN(H14:H18) -> 0.025141098 | I21: =MEDIAN(I14:I18) -> 0.85 | J21: =MEDIAN(J14:J18) -> 0.8497762
B24: Cost of Debt | G24: Cost of Equity
B26: Pre-tax Cost of Debt | E26: 0.075 | G26: Risk Free Rate | J26: 0.0685
B27: Tax Rate | E27: 0.2517 | G27: Equity Risk Premium | J27: 0.055
B28: After Tax Cost of Debt | E28: =E26*(1-E27) -> 0.0561225 | G28: Levered Beta 4 | J28: =J37 -> 0.85173046
G29: Cost of Equity | J29: =J26+J28*J27 -> 0.11534518
B32: Capital Structure | G32: Levered Beta
D34: Current | E34: Target | G34: Comps Median Unlevered Beta | J34: =J21 -> 0.8497762
B35: Total Debt | D35: 1135.05 | E35: 1135.05 | G35: Target Debt/ Equity | J35: =E39 -> 0.003073284
B36: Market Capitalization | D36: ='[1]Data Sheet'!B9 -> 369328.06 | E36: ='[1]Data Sheet'!B9 -> 369328.06 | G36: Tax Rate | J36: 0.2517
B37: Total Capitalization | D37: =D35+D36 -> 370463.11 | E37: =E35+E36 -> 370463.11 | G37: Levered Beta | J37: =J34*(1+(1-J36)*J35) -> 0.85173046
B39: Debt / Equity | D39: =D35/D36 -> 0.003073284 | E39: =E35/E36 -> 0.003073284 | G39: Weighted Average Cost of Capital
B41: 1. Tax Rate considered as Marginal Tax Rate for the country | I41: Total Cost | J41: Total Weight
B42: 2. Levered Beta is based on 5 year monthly data | G42: Debt Capital | H42: =D39 -> 0.003073284 | I42: =E28 -> 0.0561225 | J42: =H42*I42 -> 0.00017248038
B43: 3. Unlevered Beta = Levered Beta/(1+(1-Tax Rate) x Debt/Equity) | G43: Equity Capital | H43: =D36/D37 -> 0.99693613 | I43: =J29 -> 0.11534518 | J43: =H43*I43 -> 0.11499177
B44: 4. Levered Beta = Unlevered Beta*(1+(1-Tax Rate) x Debt/Equity) | G44: Weighted Average Cost of Capital | J44: =J43+J42 -> 0.11516425

Sheet Beta-Regression
B1: MAHINDRA AND MAHINDRA LTD PROJECT
B6: Mahindra and Mahindra Weekly Returns | G6: Nifty Weekly Returns | J6: Beta Drifting
B8: Date | C8: Closing price | D8: Return | G8: Closing price | H8: Return | J8: Levered raw beta | L8: =P8 -> 1.727123 | O8: Beta 1 | P8: =SLOPE(D10:D113,H10:H113) -> 1.727123
B9: Feb 27, 2023 | C9: 1236.38 | G9: 17594.35 | J9: Raw beta weight | L9: 0.75
B10: Mar 6, 2023 | C10: 1195.55 | D10: =C10/C9-1 -> -0.033023828 | G10: 17412.9 | H10: =G10/G9-1 -> -0.01031297
B11: Mar 13, 2023 | C11: 1141.75 | D11: =C11/C10-1 -> -0.045000209 | G11: 17100.05 | H11: =G11/G10-1 -> -0.017966565 | J11: market beta | L11: 1
B12: Mar 20, 2023 | C12: 1121.58 | D12: =C12/C11-1 -> -0.017665864 | G12: 16945.05 | H12: =G12/G11-1 -> -0.009064301 | J12: market beta weight | L12: 0.25
B13: Mar 27, 2023 | C13: 1129.28 | D13: =C13/C12-1 -> 0.006865315 | G13: 17359.75 | H13: =G13/G12-1 -> 0.024473224
B14: Apr 3, 2023 | C14: 1141.51 | D14: =C14/C13-1 -> 0.010829909 | G14: 17599.15 | H14: =G14/G13-1 -> 0.013790521 | J14: Adjusted beta | L14: =(L8*L9)+(L11*L12) -> 1.5453422
B15: Apr 10, 2023 | C15: 1173.96 | D15: =C15/C14-1 -> 0.028427259 | G15: 17828 | H15: =G15/G14-1 -> 0.013003469
B16: Apr 17, 2023 | C16: 1181.95 | D16: =C16/C15-1 -> 0.0068060241 | G16: 17624.05 | H16: =G16/G15-1 -> -0.01143987
B17: Apr 24, 2023 | C17: 1195.74 | D17: =C17/C16-1 -> 0.01166716 | G17: 18065 | H17: =G17/G16-1 -> 0.025019788
B18: May 1, 2023 | C18: 1180.44 | D18: =C18/C17-1 -> -0.012795424 | G18: 18069 | H18: =G18/G17-1 -> 0.00022142264
B19: May 8, 2023 | C19: 1243.55 | D19: =C19/C18-1 -> 0.053463115 | G19: 18314.8 | H19: =G19/G18-1 -> 0.013603409
B20: May 15, 2023 | C20: 1228.39 | D20: =C20/C19-1 -> -0.012190905 | G20: 18203.4 | H20: =G20/G19-1 -> -0.0060825125
B21: May 22, 2023 | C21: 1249.3 | D21: =C21/C20-1 -> 0.017022281 | G21: 18499.35 | H21: =G21/G20-1 -> 0.016257952
B22: May 29, 2023 | C22: 1307.34 | D22: =C22/C21-1 -> 0.046458016 | G22: 18534.1 | H22: =G22/G21-1 -> 0.0018784444
B23: Jun 5, 2023 | C23: 1335.84 | D23: =C23/C22-1 -> 0.021799991 | G23: 18563.4 | H23: =G23/G22-1 -> 0.0015808699
B24: Jun 12, 2023 | C24: 1368.2 | D24: =C24/C23-1 -> 0.024224458 | G24: 18826 | H24: =G24/G23-1 -> 0.014146115
B25: Jun 19, 2023 | C25: 1338.38 | D25: =C25/C24-1 -> -0.021795059 | G25: 18665.5 | H25: =G25/G24-1 -> -0.0085254435
B26: Jun 26, 2023 | C26: 1416.69 | D26: =C26/C25-1 -> 0.058511036 | G26: 19189.05 | H26: =G26/G25-1 -> 0.028049074
... B113: Feb 24, 2025 | C113: 2564.5 | D113: =C113/C112-1 -> -0.031562491 | G113: 22124.7 | H113: =G113/G112-1 -> -0.029443891
